savify/__init__.py
savify/__main__.py
savify/cli.py
savify/exceptions.py
savify/ffmpegdl.py
savify/logger.py
savify/savify.py
savify/spotify.py
savify/track.py
savify/types.py
savify/utils.py
savify2-2.3.5.dist-info/licenses/AUTHORS.rst
savify2-2.3.5.dist-info/licenses/LICENSE
savify2-2.3.5.dist-info/METADATA
savify2-2.3.5.dist-info/WHEEL
savify2-2.3.5.dist-info/entry_points.txt
savify2-2.3.5.dist-info/top_level.txt
savify2-2.3.5.dist-info/RECORD
